{
  "2320000": "神奈川県横浜市南区",
  "2320001": "神奈川県横浜市南区伏見町",
  "2320002": "神奈川県横浜市南区三春台",
  "2320003": "神奈川県横浜市南区西中町",
  "2320004": "神奈川県横浜市南区前里町",
  "2320005": "神奈川県横浜市南区白金町",
  "2320006": "神奈川県横浜市南区南太田",
  "2320007": "神奈川県横浜市南区清水ケ丘",
  "2320008": "神奈川県横浜市南区庚台",
  "2320011": "神奈川県横浜市南区日枝町",
  "2320012": "神奈川県横浜市南区南吉田町",
  "2320013": "神奈川県横浜市南区山王町",
  "2320014": "神奈川県横浜市南区吉野町",
  "2320015": "神奈川県横浜市南区共進町",
  "2320016": "神奈川県横浜市南区宮元町",
  "2320017": "神奈川県横浜市南区宿町",
  "2320018": "神奈川県横浜市南区花之木町",
  "2320021": "神奈川県横浜市南区真金町",
  "2320022": "神奈川県横浜市南区高根町",
  "2320023": "神奈川県横浜市南区白妙町",
  "2320024": "神奈川県横浜市南区浦舟町",
  "2320025": "神奈川県横浜市南区高砂町",
  "2320026": "神奈川県横浜市南区二葉町",
  "2320027": "神奈川県横浜市南区新川町",
  "2320031": "神奈川県横浜市南区永楽町",
  "2320032": "神奈川県横浜市南区万世町",
  "2320033": "神奈川県横浜市南区中村町",
  "2320034": "神奈川県横浜市南区唐沢",
  "2320035": "神奈川県横浜市南区平楽",
  "2320036": "神奈川県横浜市南区山谷",
  "2320037": "神奈川県横浜市南区八幡町",
  "2320041": "神奈川県横浜市南区睦町",
  "2320042": "神奈川県横浜市南区堀ノ内町",
  "2320043": "神奈川県横浜市南区蒔田町",
  "2320044": "神奈川県横浜市南区榎町",
  "2320045": "神奈川県横浜市南区東蒔田町",
  "2320051": "神奈川県横浜市南区井土ケ谷上町",
  "2320052": "神奈川県横浜市南区井土ケ谷中町",
  "2320053": "神奈川県横浜市南区井土ケ谷下町",
  "2320054": "神奈川県横浜市南区大橋町",
  "2320055": "神奈川県横浜市南区中島町",
  "2320056": "神奈川県横浜市南区通町",
  "2320057": "神奈川県横浜市南区若宮町",
  "2320061": "神奈川県横浜市南区大岡",
  "2320062": "神奈川県横浜市南区中里町",
  "2320063": "神奈川県横浜市南区中里",
  "2320064": "神奈川県横浜市南区別所",
  "2320065": "神奈川県横浜市南区別所中里台",
  "2320066": "神奈川県横浜市南区六ツ川",
  "2320067": "神奈川県横浜市南区弘明寺町",
  "2320071": "神奈川県横浜市南区永田北",
  "2320072": "神奈川県横浜市南区永田東",
  "2320073": "神奈川県横浜市南区永田南",
  "2320074": "神奈川県横浜市南区永田山王台",
  "2320075": "神奈川県横浜市南区永田みなみ台",
  "2320076": "神奈川県横浜市南区永田台",
  "2328510": "神奈川県横浜市南区大岡",
  "2328515": "神奈川県横浜市南区宮元町",
  "2328531": "神奈川県横浜市南区永田台",
  "2328555": "神奈川県横浜市南区六ツ川",
  "2328558": "神奈川県横浜市南区花之木町",
  "2328580": "神奈川県横浜市南区蒔田町",
  "2328585": "神奈川県横浜市南区宿町",
  "2328587": "神奈川県横浜市南区唐沢",
  "2328602": "神奈川県横浜市南区弘明寺町",
  "2328688": "神奈川県横浜市南区中里"
}