{
  "7960000": "愛媛県八幡浜市",
  "7960001": "愛媛県八幡浜市向灘",
  "7960002": "愛媛県八幡浜市大平",
  "7960003": "愛媛県八幡浜市大平",
  "7960004": "愛媛県八幡浜市大平",
  "7960005": "愛媛県八幡浜市高野地",
  "7960010": "愛媛県八幡浜市松柏",
  "7960011": "愛媛県八幡浜市木多町",
  "7960012": "愛媛県八幡浜市南柏",
  "7960013": "愛媛県八幡浜市山越",
  "7960014": "愛媛県八幡浜市新和田町",
  "7960020": "愛媛県八幡浜市神宮",
  "7960021": "愛媛県八幡浜市桧谷",
  "7960022": "愛媛県八幡浜市駅前",
  "7960023": "愛媛県八幡浜市神宮前",
  "7960024": "愛媛県八幡浜市神宮通",
  "7960025": "愛媛県八幡浜市東矢野町",
  "7960026": "愛媛県八幡浜市矢野町",
  "7960027": "愛媛県八幡浜市松蔭町",
  "7960028": "愛媛県八幡浜市清水町",
  "7960029": "愛媛県八幡浜市花小路",
  "7960031": "愛媛県八幡浜市江戸岡",
  "7960032": "愛媛県八幡浜市東新川",
  "7960033": "愛媛県八幡浜市大正町",
  "7960034": "愛媛県八幡浜市浜田町",
  "7960035": "愛媛県八幡浜市須崎",
  "7960036": "愛媛県八幡浜市新川",
  "7960037": "愛媛県八幡浜市昭和通",
  "7960038": "愛媛県八幡浜市清水町花小路",
  "7960041": "愛媛県八幡浜市裁判所通",
  "7960042": "愛媛県八幡浜市喜多町",
  "7960043": "愛媛県八幡浜市東近江屋町",
  "7960044": "愛媛県八幡浜市西近江屋町",
  "7960045": "愛媛県八幡浜市西近江屋町浜通",
  "7960046": "愛媛県八幡浜市旧港",
  "7960047": "愛媛県八幡浜市白浜通",
  "7960048": "愛媛県八幡浜市北浜",
  "7960051": "愛媛県八幡浜市幸町",
  "7960052": "愛媛県八幡浜市松本町",
  "7960053": "愛媛県八幡浜市海望園",
  "7960054": "愛媛県八幡浜市琴平町",
  "7960055": "愛媛県八幡浜市大門",
  "7960056": "愛媛県八幡浜市愛宕",
  "7960057": "愛媛県八幡浜市愛宕山団地",
  "7960061": "愛媛県八幡浜市海老崎",
  "7960062": "愛媛県八幡浜市新栄町",
  "7960063": "愛媛県八幡浜市横町",
  "7960064": "愛媛県八幡浜市船場通",
  "7960065": "愛媛県八幡浜市片山町",
  "7960066": "愛媛県八幡浜市本町",
  "7960067": "愛媛県八幡浜市中央",
  "7960068": "愛媛県八幡浜市浜之町",
  "7960069": "愛媛県八幡浜市下道",
  "7960071": "愛媛県八幡浜市新町",
  "7960072": "愛媛県八幡浜市港町",
  "7960073": "愛媛県八幡浜市戎町",
  "7960074": "愛媛県八幡浜市新港",
  "7960075": "愛媛県八幡浜市仲之町",
  "7960076": "愛媛県八幡浜市千代田町",
  "7960077": "愛媛県八幡浜市旧役場前通",
  "7960079": "愛媛県八幡浜市新港戎町",
  "7960081": "愛媛県八幡浜市朝潮橋",
  "7960082": "愛媛県八幡浜市北大黒町",
  "7960083": "愛媛県八幡浜市大黒町",
  "7960084": "愛媛県八幡浜市南大黒町",
  "7960085": "愛媛県八幡浜市天神通",
  "7960086": "愛媛県八幡浜市旭町",
  "7960087": "愛媛県八幡浜市沖新田",
  "7960088": "愛媛県八幡浜市",
  "7960089": "愛媛県八幡浜市出島",
  "7960111": "愛媛県八幡浜市保内町喜木",
  "7960112": "愛媛県八幡浜市保内町須川",
  "7960170": "愛媛県八幡浜市日土町",
  "7960201": "愛媛県八幡浜市保内町川之石",
  "7960202": "愛媛県八幡浜市保内町宮内",
  "7960203": "愛媛県八幡浜市保内町磯崎",
  "7960204": "愛媛県八幡浜市保内町喜木津",
  "7960205": "愛媛県八幡浜市保内町広早",
  "7960292": "愛媛県八幡浜市保内町宮内",
  "7960293": "愛媛県八幡浜市保内町宮内",
  "7960295": "愛媛県八幡浜市保内町川之石",
  "7960300": "愛媛県西宇和郡伊方町",
  "7960301": "愛媛県西宇和郡伊方町湊浦",
  "7960302": "愛媛県西宇和郡伊方町小中浦",
  "7960303": "愛媛県西宇和郡伊方町亀浦",
  "7960304": "愛媛県西宇和郡伊方町伊方越",
  "7960305": "愛媛県西宇和郡伊方町河内",
  "7960306": "愛媛県西宇和郡伊方町仁田之浜",
  "7960307": "愛媛県西宇和郡伊方町中之浜",
  "7960308": "愛媛県西宇和郡伊方町大浜",
  "7960311": "愛媛県西宇和郡伊方町中浦",
  "7960312": "愛媛県西宇和郡伊方町川永田",
  "7960313": "愛媛県西宇和郡伊方町豊之浦",
  "7960421": "愛媛県西宇和郡伊方町九町",
  "7960422": "愛媛県西宇和郡伊方町二見",
  "7960495": "愛媛県西宇和郡伊方町九町",
  "7960501": "愛媛県西宇和郡伊方町足成",
  "7960502": "愛媛県西宇和郡伊方町三机",
  "7960503": "愛媛県西宇和郡伊方町大江",
  "7960504": "愛媛県西宇和郡伊方町志津",
  "7960505": "愛媛県西宇和郡伊方町小島",
  "7960506": "愛媛県西宇和郡伊方町塩成",
  "7960611": "愛媛県西宇和郡伊方町川之浜",
  "7960612": "愛媛県西宇和郡伊方町大久",
  "7960613": "愛媛県西宇和郡伊方町神崎",
  "7960614": "愛媛県西宇和郡伊方町田部",
  "7960615": "愛媛県西宇和郡伊方町高茂",
  "7960801": "愛媛県西宇和郡伊方町三崎",
  "7960802": "愛媛県西宇和郡伊方町高浦",
  "7960803": "愛媛県西宇和郡伊方町佐田",
  "7960804": "愛媛県西宇和郡伊方町大佐田",
  "7960805": "愛媛県西宇和郡伊方町井野浦",
  "7960811": "愛媛県西宇和郡伊方町松",
  "7960812": "愛媛県西宇和郡伊方町明神",
  "7960813": "愛媛県西宇和郡伊方町二名津",
  "7960814": "愛媛県西宇和郡伊方町平礒",
  "7960815": "愛媛県西宇和郡伊方町釜木",
  "7960816": "愛媛県西宇和郡伊方町名取",
  "7960821": "愛媛県西宇和郡伊方町与侈",
  "7960822": "愛媛県西宇和郡伊方町串",
  "7960823": "愛媛県西宇和郡伊方町正野",
  "7960901": "愛媛県西予市三瓶町周木",
  "7960902": "愛媛県西予市三瓶町長早",
  "7960903": "愛媛県西予市三瓶町二及",
  "7960904": "愛媛県西予市三瓶町垣生",
  "7960905": "愛媛県西予市三瓶町鴫山",
  "7960906": "愛媛県西予市三瓶町和泉",
  "7960907": "愛媛県西予市三瓶町朝立",
  "7960908": "愛媛県西予市三瓶町津布理",
  "7960909": "愛媛県西予市三瓶町安土",
  "7960910": "愛媛県西予市三瓶町有網代",
  "7960911": "愛媛県西予市三瓶町有太刀",
  "7960912": "愛媛県西予市三瓶町蔵貫浦",
  "7960913": "愛媛県西予市三瓶町蔵貫",
  "7960914": "愛媛県西予市三瓶町皆江",
  "7960915": "愛媛県西予市三瓶町下泊",
  "7968001": "愛媛県八幡浜市大谷口",
  "7968002": "愛媛県八幡浜市広瀬",
  "7968003": "愛媛県八幡浜市古町",
  "7968004": "愛媛県八幡浜市産業通",
  "7968005": "愛媛県八幡浜市矢野町",
  "7968006": "愛媛県八幡浜市八代",
  "7968007": "愛媛県八幡浜市八代",
  "7968008": "愛媛県八幡浜市栗野浦",
  "7968010": "愛媛県八幡浜市五反田",
  "7968011": "愛媛県八幡浜市元城団地",
  "7968015": "愛媛県八幡浜市国木",
  "7968020": "愛媛県八幡浜市郷",
  "7968025": "愛媛県八幡浜市川之内",
  "7968030": "愛媛県八幡浜市中津川",
  "7968035": "愛媛県八幡浜市若山",
  "7968036": "愛媛県八幡浜市釜倉",
  "7968037": "愛媛県八幡浜市谷",
  "7968038": "愛媛県八幡浜市横平",
  "7968039": "愛媛県八幡浜市布喜川",
  "7968040": "愛媛県八幡浜市舌間",
  "7968041": "愛媛県八幡浜市合田",
  "7968050": "愛媛県八幡浜市川上町川名津",
  "7968051": "愛媛県八幡浜市川上町上泊",
  "7968052": "愛媛県八幡浜市川上町白石",
  "7968053": "愛媛県八幡浜市真網代",
  "7968054": "愛媛県八幡浜市穴井",
  "7968060": "愛媛県八幡浜市大島",
  "7968501": "愛媛県八幡浜市北浜",
  "7968502": "愛媛県八幡浜市大平"
}